thumbor_arcface/__init__.py
thumbor_arcface/__pycache__/__init__.cpython-39.pyc
thumbor_arcface/arcface/engine.py
thumbor_arcface/arcface/lib_func.py
thumbor_arcface/arcface/struct_info.py
thumbor_arcface/arcface/__pycache__/engine.cpython-39.pyc
thumbor_arcface/arcface/__pycache__/lib_func.cpython-39.pyc
thumbor_arcface/arcface/__pycache__/struct_info.cpython-39.pyc
thumbor_arcface/lib/libarcsoft_face.so
thumbor_arcface/lib/libarcsoft_face_engine.so
thumbor_arcface-0.1.7.dist-info/LICENSE
thumbor_arcface-0.1.7.dist-info/METADATA
thumbor_arcface-0.1.7.dist-info/WHEEL
thumbor_arcface-0.1.7.dist-info/top_level.txt
thumbor_arcface-0.1.7.dist-info/RECORD
