Metadata-Version: 2.1
Name: thumbor-arcface
Version: 0.1.7
Summary: Enable thumbor to use ArcFace to run face detection
Home-page: https://github.com/lanrenwo/thumbor_arcface
Author: lanrenwo
Author-email: phpcleps@gmail.com
License: MIT
License-File: LICENSE
Requires-Dist: thumbor >=7.0.0
